veritas/__init__.py
veritas/cache.py
veritas/core.py
veritas/datastructs.py
veritas/exceptions.py
veritas_mem-0.1.1.dist-info/METADATA
veritas_mem-0.1.1.dist-info/WHEEL
veritas_mem-0.1.1.dist-info/RECORD
