Metadata-Version: 2.3
Name: veritas-mem
Version: 0.1.1
Summary: Veritas is a minimal Python microframework that enables safe usage of shared mutable default arguments in functions.
Author: parzi-val
Author-email: krbala1511@gmail.com
Requires-Python: >=3.11
Classifier: Programming Language :: Python :: 3
Classifier: Programming Language :: Python :: 3.11
Classifier: Programming Language :: Python :: 3.12
Classifier: Programming Language :: Python :: 3.13
Project-URL: Homepage, https://earthy-shrimp-457.notion.site/veritas-mutable-defaults-to-lambda-classes-24147640429a809ba1ced30cdbe320a4
